pyzanata/__init__.py
pyzanata/restapi.yaml
pyzanata/tests.py
pyzanata-1.0b1.dist-info/DESCRIPTION.rst
pyzanata-1.0b1.dist-info/METADATA
pyzanata-1.0b1.dist-info/RECORD
pyzanata-1.0b1.dist-info/WHEEL
pyzanata-1.0b1.dist-info/metadata.json
pyzanata-1.0b1.dist-info/top_level.txt
