Metadata-Version: 2.0
Name: pyzanata
Version: 1.0b1
Summary: RESTAPI Client for the ZANATA translation web-service
Home-page: https://pypi.python.org/pypi/pyzanata
Author: Jens W. Klein
Author-email: jk@kleinundpartner.at
License: BSD License
Keywords: zanata rest api client
Platform: UNKNOWN
Classifier: Programming Language :: Python
Classifier: Programming Language :: Python :: 2.7
Classifier: Operating System :: OS Independent
Classifier: License :: OSI Approved :: BSD License
Requires-Dist: pyyaml
Requires-Dist: requests
Requires-Dist: setuptools
Provides-Extra: dev
Requires-Dist: pdbpp; extra == 'dev'
Provides-Extra: test
Requires-Dist: responses; extra == 'test'
